{
  "Make": "Audi",
  "Models": [
    {
      "Model": "100",
      "Generations": [
        "1990—1994 C4",
        "1988—1991 C3 рестайлинг",
        "1982—1988 C3",
        "1976—1983 C2"
      ]
    },
    {
      "Model": "200",
      "Generations": [
        "1988—1991 C3 рестайлинг",
        "1983—1988 C3",
        "1979—1982 C2"
      ]
    },
    {
      "Model": "80",
      "Generations": [
        "1991—1996 B4",
        "1986—1991 B3",
        "1978—1986 B2"
      ]
    },
    {
      "Model": "90",
      "Generations": [
        "1992—1995 B4",
        "1987—1991 B3",
        "1984—1987 B2"
      ]
    },
    {
      "Model": "A1",
      "Generations": [
        "2018—2024 GB",
        "2014—2018 8X рестайлинг",
        "2010—2015 8X"
      ]
    },
    {
      "Model": "A2",
      "Generations": [
        "2000—2007 8Z"
      ]
    },
    {
      "Model": "A3",
      "Generations": [
        "2020—2024 8Y",
        "2016—2020 8V рестайлинг",
        "2012—2016 8V",
        "2008—2013 8P рестайлинг 2",
        "2004—2008 8P рестайлинг",
        "2003—2005 8P",
        "2000—2003 8L рестайлинг",
        "1996—2000 8L"
      ]
    },
    {
      "Model": "A4",
      "Generations": [
        "2019—2024 B9 рестайлинг",
        "2015—2020 B9",
        "2011—2015 B8 рестайлинг",
        "2007—2012 B8",
        "2004—2009 B7",
        "2000—2006 B6",
        "1999—2001 B5 рестайлинг",
        "1994—1999 B5"
      ]
    },
    {
      "Model": "A4 Allroad Quattro",
      "Generations": [
        "2019—2024 B9 рестайлинг",
        "2016—2020 B9",
        "2011—2016 B8 рестайлинг",
        "2009—2011 B8"
      ]
    },
    {
      "Model": "A5",
      "Generations": [
        "2019—2024 II рестайлинг",
        "2016—2020 II",
        "2011—2016 I рестайлинг",
        "2007—2011 I"
      ]
    },
    {
      "Model": "A6",
      "Generations": [
        "2022—2024 C8 рестайлинг",
        "2018—2023 C8",
        "2014—2018 C7 рестайлинг",
        "2011—2014 C7",
        "2008—2011 C6 рестайлинг",
        "2004—2008 С6",
        "2001—2004 C5 рестайлинг",
        "1997—2001 C5",
        "1994—1997 C4"
      ]
    },
    {
      "Model": "A6 Allroad Quattro",
      "Generations": [
        "2019—2024 C8",
        "2014—2019 C7 рестайлинг",
        "2012—2014 C7",
        "2008—2011 C6 рестайлинг",
        "2006—2008 C6",
        "2000—2006 C5"
      ]
    },
    {
      "Model": "A7",
      "Generations": [
        "2018—2023 II",
        "2014—2018 I рестайлинг",
        "2010—2014 I"
      ]
    },
    {
      "Model": "A7L",
      "Generations": [
        "2021—2024 C8"
      ]
    },
    {
      "Model": "A8",
      "Generations": [
        "2021—2024 D5 рестайлинг",
        "2017—2022 D5",
        "2013—2017 D4 рестайлинг",
        "2010—2014 D4",
        "2007—2010 D3 рестайлинг 2",
        "2005—2007 D3 рестайлинг",
        "2002—2005 D3",
        "1999—2002 D2 рестайлинг",
        "1994—1999 D2"
      ]
    },
    {
      "Model": "Cabriolet",
      "Generations": [
        "1991—2000 I"
      ]
    },
    {
      "Model": "Coupe",
      "Generations": [
        "1991—1996 B3 рестайлинг",
        "1988—1991 B3",
        "1984—1988 B2 рестайлинг",
        "1980—1984 B2"
      ]
    },
    {
      "Model": "Q2",
      "Generations": [
        "2020—2024 I рестайлинг",
        "2016—2020 I"
      ]
    },
    {
      "Model": "Q2L e-tron",
      "Generations": [
        "2020—2024 I"
      ]
    },
    {
      "Model": "Q3",
      "Generations": [
        "2018—2024 II",
        "2014—2018 I рестайлинг",
        "2011—2014 I"
      ]
    },
    {
      "Model": "Q3 Sportback",
      "Generations": [
        "2019—2024 F3"
      ]
    },
    {
      "Model": "Q4 e-tron",
      "Generations": [
        "2021—2024 I"
      ]
    },
    {
      "Model": "Q5",
      "Generations": [
        "2020—2024 II рестайлинг",
        "2016—2020 II",
        "2012—2017 I рестайлинг",
        "2008—2012 I"
      ]
    },
    {
      "Model": "Q5 Sportback",
      "Generations": [
        "2020—2024 FY"
      ]
    },
    {
      "Model": "Q5 e-tron",
      "Generations": [
        "2022—2024 I"
      ]
    },
    {
      "Model": "Q5L",
      "Generations": [
        "2020—2024 FY рестайлинг",
        "2017—2020 FY"
      ]
    },
    {
      "Model": "Q6",
      "Generations": [
        "2022—2024 I"
      ]
    },
    {
      "Model": "Q7",
      "Generations": [
        "2024—2024 4M рестайлинг 2",
        "2019—2024 4M рестайлинг",
        "2015—2020 4M",
        "2009—2015 4L рестайлинг",
        "2005—2009 4L"
      ]
    },
    {
      "Model": "Q8",
      "Generations": [
        "2023—2024 I рестайлинг",
        "2018—2023 I"
      ]
    },
    {
      "Model": "Q8 Sportback e-tron",
      "Generations": [
        "2022—2024 I"
      ]
    },
    {
      "Model": "Q8 e-tron",
      "Generations": [
        "2022—2024 I"
      ]
    },
    {
      "Model": "Quattro",
      "Generations": [
        "1985—1991 I рестайлинг",
        "1980—1985 I"
      ]
    },
    {
      "Model": "R8",
      "Generations": [
        "2019—2024 II рестайлинг",
        "2015—2019 II",
        "2012—2015 I рестайлинг",
        "2007—2012 I"
      ]
    },
    {
      "Model": "RS Q3",
      "Generations": [
        "2019—2024 F3",
        "2015—2018 8U рестайлинг",
        "2013—2015 8U"
      ]
    },
    {
      "Model": "RS Q3 Sportback",
      "Generations": [
        "2019—2024 F3"
      ]
    },
    {
      "Model": "RS Q8",
      "Generations": [
        "2019—2024 I"
      ]
    },
    {
      "Model": "RS e-tron GT",
      "Generations": [
        "2021—2024 I"
      ]
    },
    {
      "Model": "RS2",
      "Generations": [
        "1993—1995 B4"
      ]
    },
    {
      "Model": "RS3",
      "Generations": [
        "2021—2024 8Y",
        "2017—2021 8V рестайлинг",
        "2012—2016 8V",
        "2011—2012 8P рестайлинг 2"
      ]
    },
    {
      "Model": "RS4",
      "Generations": [
        "2019—2024 B9 рестайлинг",
        "2017—2020 B9",
        "2012—2015 B8",
        "2005—2009 B7",
        "1999—2001 B5"
      ]
    },
    {
      "Model": "RS5",
      "Generations": [
        "2019—2024 F5 рестайлинг",
        "2017—2019 F5",
        "2012—2016 8T рестайлинг",
        "2010—2012 8T"
      ]
    },
    {
      "Model": "RS6",
      "Generations": [
        "2019—2024 C8",
        "2014—2018 C7 рестайлинг",
        "2012—2014 C7",
        "2007—2012 C6",
        "2002—2006 C5"
      ]
    },
    {
      "Model": "RS7",
      "Generations": [
        "2019—2024 II",
        "2014—2018 I рестайлинг",
        "2010—2014 I"
      ]
    },
    {
      "Model": "S2",
      "Generations": [
        "1990—1995 I"
      ]
    },
    {
      "Model": "S3",
      "Generations": [
        "2020—2024 8Y",
        "2016—2020 8V рестайлинг",
        "2012—2016 8V",
        "2008—2012 8P рестайлинг 2",
        "2006—2008 8P",
        "1999—2003 8L"
      ]
    },
    {
      "Model": "S4",
      "Generations": [
        "2019—2024 B9 рестайлинг",
        "2016—2019 B9",
        "2011—2015 B8 рестайлинг",
        "2008—2011 B8",
        "2004—2008 B7",
        "2002—2004 B6",
        "1997—2001 B5"
      ]
    },
    {
      "Model": "S5",
      "Generations": [
        "2019—2024 II рестайлинг",
        "2016—2019 II",
        "2011—2016 I рестайлинг",
        "2007—2011 I"
      ]
    },
    {
      "Model": "S6",
      "Generations": [
        "2019—2024 C8",
        "2014—2018 C7 рестайлинг",
        "2012—2014 C7",
        "2008—2011 C6 рестайлинг",
        "2006—2008 C6",
        "1999—2004 C5",
        "1994—1997 C4"
      ]
    },
    {
      "Model": "S7",
      "Generations": [
        "2019—2024 4K",
        "2014—2018 I рестайлинг",
        "2010—2014 I"
      ]
    },
    {
      "Model": "S8",
      "Generations": [
        "2019—2023 D5",
        "2013—2018 D4 рестайлинг",
        "2012—2013 D4",
        "2007—2011 D3 рестайлинг",
        "2006—2007 D3",
        "1999—2002 D2 рестайлинг",
        "1996—1999 D2"
      ]
    },
    {
      "Model": "SQ5",
      "Generations": [
        "2020—2024 II рестайлинг",
        "2017—2020 II",
        "2013—2017 I"
      ]
    },
    {
      "Model": "SQ5 Sportback",
      "Generations": [
        "2020—2024 FY"
      ]
    },
    {
      "Model": "SQ7",
      "Generations": [
        "2019—2024 4M рестайлинг",
        "2016—2019 4M"
      ]
    },
    {
      "Model": "SQ8",
      "Generations": [
        "2023—2024 I рестайлинг",
        "2019—2023 I"
      ]
    },
    {
      "Model": "TT",
      "Generations": [
        "2018—2024 8S рестайлинг",
        "2014—2019 8S",
        "2010—2014 8J рестайлинг",
        "2006—2010 8J",
        "2003—2006 8N рестайлинг",
        "1998—2003 8N"
      ]
    },
    {
      "Model": "TT RS",
      "Generations": [
        "2019—2024 8S рестайлинг",
        "2016—2018 8S",
        "2009—2014 8J"
      ]
    },
    {
      "Model": "TTS",
      "Generations": [
        "2018—2024 8S рестайлинг",
        "2014—2018 8S",
        "2010—2014 8J рестайлинг",
        "2007—2010 8J"
      ]
    },
    {
      "Model": "V8",
      "Generations": [
        "1988—1994 4C"
      ]
    },
    {
      "Model": "e-tron",
      "Generations": [
        "2018—2024 I"
      ]
    },
    {
      "Model": "e-tron GT",
      "Generations": [
        "2020—2024 I"
      ]
    },
    {
      "Model": "e-tron S",
      "Generations": [
        "2020—2024 I"
      ]
    },
    {
      "Model": "e-tron S Sportback",
      "Generations": [
        "2020—2024 I"
      ]
    },
    {
      "Model": "e-tron Sportback",
      "Generations": [
        "2019—2024 I"
      ]
    }
  ]
}